KayPacha-0.0.5.data/scripts/kaypacha_blockdiag
KayPacha-0.0.5.data/scripts/kaypacha_scienti
KayPacha-0.0.5.data/scripts/kaypacha_siiu
kaypacha/__init__.py
kaypacha/_version.py
kaypacha/filters/__init__.py
kaypacha/filters/scienti_filter.py
kaypacha/filters/siiu_filter.py
kaypacha/models/__init__.py
kaypacha/models/scienti/__init__.py
kaypacha/models/scienti/graph_fields.py
kaypacha/models/scienti/graph_fields_author.py
kaypacha/models/scienti/graph_fields_endorsement.py
kaypacha/models/scienti/graph_fields_event.py
kaypacha/models/scienti/graph_fields_network.py
kaypacha/models/scienti/graph_fields_patent.py
kaypacha/models/scienti/graph_fields_product.py
kaypacha/models/scienti/graph_fields_project.py
kaypacha/models/scienti/graph_schema.py
kaypacha/models/scienti/graph_schema_author.py
kaypacha/models/scienti/graph_schema_endorsement.py
kaypacha/models/scienti/graph_schema_event.py
kaypacha/models/scienti/graph_schema_network.py
kaypacha/models/scienti/graph_schema_patent.py
kaypacha/models/scienti/graph_schema_product.py
kaypacha/models/scienti/graph_schema_project.py
kaypacha/models/siiu/__init__.py
kaypacha/models/siiu/graph_fields.py
kaypacha/models/siiu/graph_fields_call.py
kaypacha/models/siiu/graph_fields_project.py
kaypacha/models/siiu/graph_schema.py
kaypacha/models/siiu/graph_schema_call.py
kaypacha/models/siiu/graph_schema_project.py
KayPacha-0.0.5.dist-info/LICENSE
KayPacha-0.0.5.dist-info/METADATA
KayPacha-0.0.5.dist-info/WHEEL
KayPacha-0.0.5.dist-info/top_level.txt
KayPacha-0.0.5.dist-info/RECORD
