Metadata-Version: 2.1
Name: KayPacha
Version: 0.0.5
Summary: SQL data extraction for Scienti and UdeA Oracle databases
Home-page: https://github.com/colav/KayPacha
Author: Colav
Author-email: colav@udea.edu.co
License: BSD
License-File: LICENSE
Requires-Dist: pandas
Requires-Dist: numpy
Requires-Dist: ukupacha
Requires-Dist: cx-Oracle
Requires-Dist: psutil
Requires-Dist: pymongo >=3.12.0
Requires-Dist: joblib >=1.1.0
